<?xml version="1.0" encoding="UTF-8"?>
<window id="56">
  <defaultcontrol always="true">1</defaultcontrol>
  <coordinates>
    <origin x="0" y="0"/>
  </coordinates>

  <onunload>RunScript(script.skinshortcuts,type=buildxml&amp;mainmenuID=8000&amp;group=mainmenu|videohub-list|videohub-widgets)</onunload>
  <!-- <onunload>RunScript(special://skin/extras/scripts/alaskab_utils.py,updateSkinshortcutsInclude,type=buildxml&amp;mainmenuID=8000&amp;group=mainmenu|videohub-list|videohub-widgets)</onunload> -->

  <controls>
    <include>Global_Background</include>

    <control type="group" id="5000">
      <centertop>50%</centertop>
      <left>SkinSettingsLeft</left>
      <width>SkinSettingsWidth</width>
      <height>SkinSettingsHeight</height>

      <include>Animation_ZoomInZoomOut</include>
      <include>Animation_ZoomedByMenu</include>
      <animation type="Conditional" condition="Window.IsActive(shutdownmenu) | Window.IsActive(progressdialog) | Window.IsActive(okdialog) | Window.IsActive(virtualkeyboard) | Window.IsActive(filebrowser) | Window.IsActive(numericinput) | Window.IsActive(addonsettings)">
        <include>AnimationEffect_ZoomedBy</include>
      </animation>

      <control type="image">
        <width>SkinSettingsWidth</width>
        <height>SkinSettingsHeight</height>
        <visible>!Control.IsVisible(8800)</visible>
        <texture>settings/settings-category-bg.png</texture>
      </control>
      <control type="image">
        <width>SkinSettingsWidth</width>
        <height>SkinSettingsHeight</height>
        <visible>Control.IsVisible(8800)</visible>
        <texture>settings/settings-category-bg-scrollbar.png</texture>
      </control>

      <control type="group">
        <left>160</left>

        <!-- Left grouplist -->
        <control type="grouplist" id="1">
          <left>SkinSettingsLeftGLLeft</left>
          <top>SkinSettingsGLTop</top>
          <width>SkinSettingsLeftGLWidth</width>
          <height>SkinSettingsGLHeight</height>
          <itemgap>0</itemgap>
          <onright condition="Control.HasFocus(10)">1001</onright>
          <onright condition="Control.HasFocus(11)">1101</onright>
          <onright condition="Control.HasFocus(12)">1201</onright>
          <onright condition="Control.HasFocus(13)">1301</onright>
          <onright condition="Control.HasFocus(14)">1401</onright>
          <onup>noop</onup>
          <ondown>noop</ondown>
          <orientation>vertical</orientation>
          <scrolltime tween="sine" easing="out">320</scrolltime>

          <!-- Fanart -->
          <control type="button" id="10">
            <label>Backgrounds</label>
            <onclick>SetFocus(1001)</onclick>
            <include>SkinSettingsLeftGLTemplate</include>
          </control>
          <!-- Look -->
          <control type="button" id="11">
            <label>Look Settings</label>
            <onclick>SetFocus(1101)</onclick>
            <include>SkinSettingsLeftGLTemplate</include>
          </control>
          <!-- Home -->
          <control type="button" id="12">
            <label>Home Settings</label>
            <onclick>SetFocus(1201)</onclick>
            <include>SkinSettingsLeftGLTemplate</include>
          </control>
          <!-- Debug -->
          <control type="button" id="13">
            <label>31033</label>
            <onclick>SetFocus(1301)</onclick>
            <include>SkinSettingsLeftGLTemplate</include>
          </control>
          <control type="button" id="14">
            <label>AlaskaB</label>
            <onclick>SetFocus(1401)</onclick>
            <include>SkinSettingsLeftGLTemplate</include>
          </control>
        </control>

        <!-- Right grouplists -->
        <control type="group" id="1000">
          <visible>Control.HasFocus(10) | ControlGroup(1000).HasFocus()</visible>

          <control type="grouplist" id="1001">
            <left>SkinSettingsRightGLLeft</left>
            <top>SkinSettingsGLTop</top>
            <width>SkinSettingsRightGLWidth</width>
            <height>SkinSettingsGLHeight</height>
            <itemgap>0</itemgap>
            <onleft>1</onleft>
            <onright>8800</onright>
            <pagecontrol>8800</pagecontrol>
            <orientation>vertical</orientation>
            <scrolltime tween="sine" easing="out">320</scrolltime>

            <!-- Background image -->
            <control type="togglebutton" id="1011">
              <include>SkinSettingsRightGLTemplateWithText</include>
              <label>Set Background image</label>
              <altlabel>Background image</altlabel>
              <onclick>Skin.Reset(Background_Image)</onclick>
              <onclick>Skin.SetImage(Background_Image)</onclick>
              <usealttexture>!IsEmpty(Skin.String(Background_Image))</usealttexture>
            </control>
            <!-- Movie Fanart -->
            <control type="radiobutton" id="1012">
              <include>SkinSettingsRightGLTemplateWithText</include>
              <label>Disable Movie Fanart</label>
              <onclick>Skin.ToggleSetting(Disable_Movie_Fanart)</onclick>
              <selected>Skin.HasSetting(Disable_Movie_Fanart)</selected>
            </control>
            <!-- TV Fanart -->
            <control type="radiobutton" id="1013">
              <include>SkinSettingsRightGLTemplateWithText</include>
              <label>Disable TV Fanart</label>
              <onclick>Skin.ToggleSetting(Disable_TV_Fanart)</onclick>
              <selected>Skin.HasSetting(Disable_TV_Fanart)</selected>
            </control>
            <!-- Music Fanart -->
            <control type="radiobutton" id="1014">
              <include>SkinSettingsRightGLTemplateWithText</include>
              <label>Disable Music Fanart</label>
              <onclick>Skin.ToggleSetting(Disable_Music_Fanart)</onclick>
              <selected>Skin.HasSetting(Disable_Music_Fanart)</selected>
            </control>
            <!-- Addon Fanart -->
            <control type="radiobutton" id="1015">
              <include>SkinSettingsRightGLTemplateWithText</include>
              <label>Disable Addon Fanart</label>
              <onclick>Skin.ToggleSetting(Disable_Addon_Fanart)</onclick>
              <selected>Skin.HasSetting(Disable_Addon_Fanart)</selected>
            </control>
          </control>

          <!-- Scrollbar -->
          <control type="scrollbar" id="8800">
            <left>1809</left>
            <top>52</top>
            <height>496</height>
            <onleft>1001</onleft>
            <visible>Skin.HasSetting(AlaskaB.Settings.SkinSettings.Scrollbar.Enable)</visible>
          </control>
        </control>

        <control type="group" id="1100">
          <visible>Control.HasFocus(11) | ControlGroup(1100).HasFocus()</visible>

          <control type="grouplist" id="1101">
            <left>SkinSettingsRightGLLeft</left>
            <top>SkinSettingsGLTop</top>
            <width>SkinSettingsRightGLWidth</width>
            <height>SkinSettingsGLHeight</height>
            <itemgap>0</itemgap>
            <onleft>1</onleft>
            <onright>8800</onright>
            <pagecontrol>8800</pagecontrol>
            <orientation>vertical</orientation>
            <scrolltime tween="sine" easing="out">320</scrolltime>

            <!-- Hide Watched Status -->
            <control type="radiobutton" id="1111">
              <include>SkinSettingsRightGLTemplateWithText</include>
              <label>Hide Watched Status</label>
              <onclick>Skin.ToggleSetting(HideWatchedOverlays)</onclick>
              <selected>Skin.HasSetting(HideWatchedOverlays)</selected>
            </control>

            <!-- Hide Resume Status -->
            <control type="radiobutton" id="1112">
              <include>SkinSettingsRightGLTemplateWithText</include>
              <label>Hide Resume Status</label>
              <onclick>Skin.ToggleSetting(HideResumeOverlays)</onclick>
              <selected>Skin.HasSetting(HideResumeOverlays)</selected>
            </control>

            <!-- RSS Home Only -->
            <control type="radiobutton" id="1113">
              <include>SkinSettingsRightGLTemplateWithText</include>
              <label>Disable Global RSS</label>
              <onclick>Skin.ToggleSetting(Disable_Global_RSS)</onclick>
              <selected>Skin.HasSetting(Disable_Global_RSS)</selected>
            </control>

            <!-- Swap Studio flag for Rating -->
            <control type="radiobutton" id="1114">
              <include>SkinSettingsRightGLTemplateWithText</include>
              <label>Swap Studio flag for Rating</label>
              <onclick>Skin.ToggleSetting(SwapStudio_Rating)</onclick>
              <selected>Skin.HasSetting(SwapStudio_Rating)</selected>
            </control>

            <!-- Open Playlists via Favourites (Default: Play) -->
            <control type="radiobutton" id="1115">
              <include>SkinSettingsRightGLTemplateWithText</include>
              <label>Open Playlists via Favourites submenu (Default: Play)</label>
              <onclick>Skin.ToggleSetting(OpenFavouritesPlaylist)</onclick>
              <selected>Skin.HasSetting(OpenFavouritesPlaylist)</selected>
            </control>
          </control>

          <!-- Scrollbar -->
          <control type="scrollbar" id="8800">
            <left>1809</left>
            <top>52</top>
            <height>496</height>
            <onleft>1101</onleft>
            <visible>Skin.HasSetting(AlaskaB.Settings.SkinSettings.Scrollbar.Enable)</visible>
          </control>
        </control>

        <control type="group" id="1200">
          <visible>Control.HasFocus(12) | ControlGroup(1200).HasFocus()</visible>

          <control type="grouplist" id="1201">
            <left>SkinSettingsRightGLLeft</left>
            <top>SkinSettingsGLTop</top>
            <width>SkinSettingsRightGLWidth</width>
            <height>SkinSettingsGLHeight</height>
            <itemgap>0</itemgap>
            <onleft>1</onleft>
            <onright>8800</onright>
            <pagecontrol>8800</pagecontrol>
            <orientation>vertical</orientation>
            <scrolltime tween="sine" easing="out">320</scrolltime>

            <!-- Hide Favourites Button -->
            <control type="radiobutton" id="1211">
              <include>SkinSettingsRightGLTemplateWithText</include>
              <label>Hide Favourites</label>
              <onclick>Skin.ToggleSetting(HideHomeFavourites)</onclick>
              <selected>Skin.HasSetting(HideHomeFavourites)</selected>
            </control>

            <!-- Hide Apps Button -->
            <control type="radiobutton" id="1212">
              <include>SkinSettingsRightGLTemplateWithText</include>
              <label>Hide Apps</label>
              <onclick>Skin.ToggleSetting(HideHomeApps)</onclick>
              <selected>Skin.HasSetting(HideHomeApps)</selected>
            </control>

            <!-- Hide Videos Button -->
            <control type="radiobutton" id="1213">
              <include>SkinSettingsRightGLTemplateWithText</include>
              <label>Hide Videos</label>
              <onclick>Skin.ToggleSetting(HideHomeVideos)</onclick>
              <selected>Skin.HasSetting(HideHomeVideos)</selected>
            </control>

            <!-- Hide Music Button -->
            <control type="radiobutton" id="1214">
              <include>SkinSettingsRightGLTemplateWithText</include>
              <label>Hide Music</label>
              <onclick>Skin.ToggleSetting(HideHomeMusic)</onclick>
              <selected>Skin.HasSetting(HideHomeMusic)</selected>
            </control>

            <!-- Hide Movies Button -->
            <control type="radiobutton" id="1215">
              <include>SkinSettingsRightGLTemplateWithText</include>
              <label>Hide Movies</label>
              <onclick>Skin.ToggleSetting(HideHomeMovies)</onclick>
              <selected>Skin.HasSetting(HideHomeMovies)</selected>
            </control>

            <!-- Hide TV Shows Button -->
            <control type="radiobutton" id="1216">
              <include>SkinSettingsRightGLTemplateWithText</include>
              <label>Hide TV Shows</label>
              <onclick>Skin.ToggleSetting(HideHomeTVShows)</onclick>
              <selected>Skin.HasSetting(HideHomeTVShows)</selected>
            </control>

            <!-- Hide Pictures Button -->
            <control type="radiobutton" id="1217">
              <include>SkinSettingsRightGLTemplateWithText</include>
              <label>Hide Pictures</label>
              <onclick>Skin.ToggleSetting(HideHomePictures)</onclick>
              <selected>Skin.HasSetting(HideHomePictures)</selected>
            </control>

            <!-- Hide Weather Button -->
            <control type="radiobutton" id="1218">
              <include>SkinSettingsRightGLTemplateWithText</include>
              <label>Hide Weather</label>
              <onclick>Skin.ToggleSetting(HideHomeWeather)</onclick>
              <selected>Skin.HasSetting(HideHomeWeather)</selected>
            </control>

            <!-- Hide Settings Button -->
            <control type="radiobutton" id="1219">
              <include>SkinSettingsRightGLTemplateWithText</include>
              <label>Hide Settings</label>
              <onclick>Skin.ToggleSetting(HideHomeSettings)</onclick>
              <selected>Skin.HasSetting(HideHomeSettings)</selected>
            </control>
          </control>

          <!-- Scrollbar -->
          <control type="scrollbar" id="8800">
            <left>1809</left>
            <top>52</top>
            <height>496</height>
            <onleft>1201</onleft>
            <visible>Skin.HasSetting(AlaskaB.Settings.SkinSettings.Scrollbar.Enable)</visible>
          </control>
        </control>

        <control type="group" id="1300">
          <visible>Control.HasFocus(13) | ControlGroup(1300).HasFocus()</visible>

          <control type="grouplist" id="1301">
            <left>SkinSettingsRightGLLeft</left>
            <top>SkinSettingsGLTop</top>
            <width>SkinSettingsRightGLWidth</width>
            <height>SkinSettingsGLHeight</height>
            <itemgap>0</itemgap>
            <onleft>1</onleft>
            <onright>8800</onright>
            <pagecontrol>8800</pagecontrol>
            <orientation>vertical</orientation>
            <scrolltime tween="sine" easing="out">320</scrolltime>

            <!-- Enable Debug Grid -->
            <control type="radiobutton" id="131">
              <include>SkinSettingsRightGLTemplateWithText</include>
              <label>31034</label>
              <onclick>Skin.ToggleSetting(DebugGrid)</onclick>
              <selected>Skin.HasSetting(DebugGrid)</selected>
            </control>

            <!-- Disable Debug Info -->
            <control type="radiobutton" id="132">
              <include>SkinSettingsRightGLTemplateWithText</include>
              <label>31035</label>
              <onclick>Skin.ToggleSetting(DebugInfo)</onclick>
              <selected>Skin.HasSetting(DebugInfo)</selected>
            </control>
          </control>

          <!-- Scrollbar -->
          <control type="scrollbar" id="8800">
            <left>1809</left>
            <top>52</top>
            <height>496</height>
            <onleft>1301</onleft>
            <visible>Skin.HasSetting(AlaskaB.Settings.SkinSettings.Scrollbar.Enable)</visible>
          </control>
        </control>

        <control type="group" id="1400">
          <visible>Control.HasFocus(14) | ControlGroup(1400).HasFocus()</visible>

          <control type="grouplist" id="1401">
            <left>SkinSettingsRightGLLeft</left>
            <top>SkinSettingsGLTop</top>
            <width>SkinSettingsRightGLWidth</width>
            <height>SkinSettingsGLHeight</height>
            <itemgap>0</itemgap>
            <onleft>1</onleft>
            <onright>8800</onright>
            <pagecontrol>8800</pagecontrol>
            <orientation>vertical</orientation>
            <scrolltime tween="sine" easing="out">320</scrolltime>

            <!-- Home menu style -->
            <control type="button" id="1411">
              <include>SkinSettingsRightGLTemplate</include>
              <label>Home menu style</label>
              <label2>$VAR[AlaskaBSetting_HomeMenuStyleLabel]</label2>
              <onclick>$VAR[AlaskaBSetting_HomeMenuStyleOnClick]</onclick>
            </control>
            <control type="button" id="1412">
              <include>SkinSettingsRightGLTemplate</include>
              <textoffsetx>50</textoffsetx>
              <label>VideoHub Menu</label>
              <onclick>RunScript(script.skinshortcuts,type=manage&amp;group=videohub-list)</onclick>
              <visible>System.HasAddon(script.skinshortcuts)</visible>
            </control>        
            <control type="button" id="1413">
              <include>SkinSettingsRightGLTemplate</include>
              <textoffsetx>50</textoffsetx>
              <label>VideoHub Widgets</label>
              <onclick>RunScript(script.skinshortcuts,type=manage&amp;group=videohub-widgets)</onclick>
              <visible>System.HasAddon(script.skinshortcuts)</visible>
            </control>        
            <control type="button" id="1414">
              <include>SkinSettingsRightGLTemplate</include>
              <textoffsetx>50</textoffsetx>
              <label>Main menu</label>
              <onclick>RunScript(script.skinshortcuts,type=manage&amp;group=mainmenu)</onclick>
              <visible>System.HasAddon(script.skinshortcuts)</visible>
            </control>        
            <control type="radiobutton" id="1420">
              <include>SkinSettingsRightGLTemplateWithText</include>
              <label>Enable Video library scrollbar</label>
              <onclick>Skin.ToggleSetting(AlaskaB.Settings.VideoNav.Scrollbar.Enable)</onclick>
              <selected>Skin.HasSetting(AlaskaB.Settings.VideoNav.Scrollbar.Enable)</selected>
            </control>
            <control type="radiobutton" id="1421">
              <include>SkinSettingsRightGLTemplateWithText</include>
              <label>Enable Video hub scrollbar</label>
              <onclick>Skin.ToggleSetting(AlaskaB.Settings.VideoHub.Scrollbar.Enable)</onclick>
              <selected>Skin.HasSetting(AlaskaB.Settings.VideoHub.Scrollbar.Enable)</selected>
            </control>
            <control type="radiobutton" id="1422">
              <include>SkinSettingsRightGLTemplateWithText</include>
              <label>Enable Video info plot scrollbar</label>
              <onclick>Skin.ToggleSetting(AlaskaB.Settings.VideoInfo.Plot.Scrollbar.Enable)</onclick>
              <selected>Skin.HasSetting(AlaskaB.Settings.VideoInfo.Plot.Scrollbar.Enable)</selected>
            </control>
            <control type="radiobutton" id="1423">
              <include>SkinSettingsRightGLTemplateWithText</include>
              <label>Enable Video info cast scrollbar</label>
              <onclick>Skin.ToggleSetting(AlaskaB.Settings.VideoInfo.Cast.Scrollbar.Enable)</onclick>
              <selected>Skin.HasSetting(AlaskaB.Settings.VideoInfo.Cast.Scrollbar.Enable)</selected>
            </control>
            <control type="radiobutton" id="1424">
              <include>SkinSettingsRightGLTemplateWithText</include>
              <label>Enable Dialog media source scrollbar</label>
              <onclick>Skin.ToggleSetting(AlaskaB.Settings.MediaSource.Scrollbar.Enable)</onclick>
              <selected>Skin.HasSetting(AlaskaB.Settings.MediaSource.Scrollbar.Enable)</selected>
            </control>
            <control type="radiobutton" id="1425">
              <include>SkinSettingsRightGLTemplateWithText</include>
              <label>Enable Dialog file browser scrollbar</label>
              <onclick>Skin.ToggleSetting(AlaskaB.Settings.FileBrowser.Scrollbar.Enable)</onclick>
              <selected>Skin.HasSetting(AlaskaB.Settings.FileBrowser.Scrollbar.Enable)</selected>
            </control>
            <control type="radiobutton" id="1426">
              <include>SkinSettingsRightGLTemplateWithText</include>
              <label>Enable Dialog select scrollbar</label>
              <onclick>Skin.ToggleSetting(AlaskaB.Settings.Select.Scrollbar.Enable)</onclick>
              <selected>Skin.HasSetting(AlaskaB.Settings.Select.Scrollbar.Enable)</selected>
            </control>
            <control type="radiobutton" id="1427">
              <include>SkinSettingsRightGLTemplateWithText</include>
              <label>Enable Setting category scrollbar</label>
              <onclick>Skin.ToggleSetting(AlaskaB.Settings.SettingsCategory.Scrollbar.Enable)</onclick>
              <selected>Skin.HasSetting(AlaskaB.Settings.SettingsCategory.Scrollbar.Enable)</selected>
            </control>
            <control type="radiobutton" id="1428">
              <include>SkinSettingsRightGLTemplateWithText</include>
              <label>Enable Setting profile scrollbar</label>
              <onclick>Skin.ToggleSetting(AlaskaB.Settings.SettingsProfile.Scrollbar.Enable)</onclick>
              <selected>Skin.HasSetting(AlaskaB.Settings.SettingsProfile.Scrollbar.Enable)</selected>
            </control>
            <control type="radiobutton" id="1429">
              <include>SkinSettingsRightGLTemplateWithText</include>
              <label>Enable Login screen scrollbar</label>
              <onclick>Skin.ToggleSetting(AlaskaB.Settings.LoginScreen.Scrollbar.Enable)</onclick>
              <selected>Skin.HasSetting(AlaskaB.Settings.LoginScreen.Scrollbar.Enable)</selected>
            </control>
            <control type="radiobutton" id="1430">
              <include>SkinSettingsRightGLTemplateWithText</include>
              <label>Enable AlaskaB setting scrollbar</label>
              <onclick>Skin.ToggleSetting(AlaskaB.Settings.SkinSettings.Scrollbar.Enable)</onclick>
              <selected>Skin.HasSetting(AlaskaB.Settings.SkinSettings.Scrollbar.Enable)</selected>
            </control>
          </control>

          <!-- Scrollbar -->
          <control type="scrollbar" id="8800">
            <left>1809</left>
            <top>52</top>
            <height>496</height>
            <onleft>1401</onleft>
            <visible>Skin.HasSetting(AlaskaB.Settings.SkinSettings.Scrollbar.Enable)</visible>
          </control>
        </control>
      </control>

      <!-- Settings button description -->

      <control type="textbox">
        <left>544</left>
        <top>928</top>
        <width>1260</width>
        <height>132</height>
        <label>Note: 'Settings' are now available from the Shutdown menu</label>
        <font>Font_Light_36</font>
        <textcolor>Red</textcolor>
        <visible>Skin.HasSetting(HideHomeSettings)</visible>
      </control>

    </control>

  </controls>

</window>